flinventory_gui-0.11.1.dist-info/METADATA
flinventory_gui-0.11.1.dist-info/WHEEL
flinventory_gui-0.11.1.dist-info/entry_points.txt
flinventory_gui/.gitignore
flinventory_gui/__init__.py
flinventory_gui/images.py
flinventory_gui/search.py
flinventory_gui/thing_editor.py
flinventory_gui/translation/__init__.py
flinventory_gui/translation/search.de.yml
flinventory_gui/translation/search.en.yml
flinventory_gui/translation/thing_editor.de.yml
flinventory_gui/translation/thing_editor.en.yml
flinventory_gui-0.11.1.dist-info/RECORD
