Metadata-Version: 2.1
Name: flinventory_gui
Version: 0.11.1
Summary: GUI for flinventory for viewing and editing inventory
Author-Email: flukx <flinventory-gui-flukx@612211124.xyz>
License: GPL3
Classifier: Development Status :: 3 - Alpha
Classifier: Intended Audience :: Customer Service
Classifier: Operating System :: OS Independent
Classifier: Programming Language :: Python :: 3.12
Classifier: Typing :: Typed
Project-URL: Homepage, https://codeberg.org/flukx/flinventory-gui
Project-URL: Issues, https://codeberg.org/flukx/flinventory-gui/issues
Requires-Python: >=3.12
Requires-Dist: nicegui==2.12.1
Requires-Dist: flinventory==0.9.3
Requires-Dist: i18nice[YAML]==0.15.5
Requires-Dist: filetype==1.2.0
